simpeg_drivers/__init__.py
simpeg_drivers/_version.py
simpeg_drivers/components/__init__.py
simpeg_drivers/components/data.py
simpeg_drivers/components/factories/__init__.py
simpeg_drivers/components/factories/abstract_factory.py
simpeg_drivers/components/factories/directives_factory.py
simpeg_drivers/components/factories/entity_factory.py
simpeg_drivers/components/factories/misfit_factory.py
simpeg_drivers/components/factories/receiver_factory.py
simpeg_drivers/components/factories/simpeg_factory.py
simpeg_drivers/components/factories/simulation_factory.py
simpeg_drivers/components/factories/source_factory.py
simpeg_drivers/components/factories/survey_factory.py
simpeg_drivers/components/locations.py
simpeg_drivers/components/meshes.py
simpeg_drivers/components/models.py
simpeg_drivers/components/topography.py
simpeg_drivers/components/windows.py
simpeg_drivers/depth_of_investigation/__init__.py
simpeg_drivers/depth_of_investigation/sensitivity_cutoff/__init__.py
simpeg_drivers/depth_of_investigation/sensitivity_cutoff/driver.py
simpeg_drivers/depth_of_investigation/sensitivity_cutoff/options.py
simpeg_drivers/driver.py
simpeg_drivers/electricals/__init__.py
simpeg_drivers/electricals/direct_current/__init__.py
simpeg_drivers/electricals/direct_current/pseudo_three_dimensions/driver.py
simpeg_drivers/electricals/direct_current/pseudo_three_dimensions/options.py
simpeg_drivers/electricals/direct_current/three_dimensions/__init__.py
simpeg_drivers/electricals/direct_current/three_dimensions/driver.py
simpeg_drivers/electricals/direct_current/three_dimensions/options.py
simpeg_drivers/electricals/direct_current/two_dimensions/__init__.py
simpeg_drivers/electricals/direct_current/two_dimensions/driver.py
simpeg_drivers/electricals/direct_current/two_dimensions/options.py
simpeg_drivers/electricals/driver.py
simpeg_drivers/electricals/induced_polarization/__init__.py
simpeg_drivers/electricals/induced_polarization/pseudo_three_dimensions/driver.py
simpeg_drivers-0.4.0.dist-info/METADATA
simpeg_drivers-0.4.0.dist-info/WHEEL
simpeg_drivers-0.4.0.dist-info/licenses/LICENSE
simpeg_drivers-0.4.0.dist-info/licenses/docs/THIRD_PARTY_SOFTWARE.rst
simpeg_drivers-0.4.0.dist-info/RECORD
