Metadata-Version: 2.4
Name: simpeg-drivers
Version: 0.4.0
Summary: Application to run SimPEG inversions with geoh5 files from Geoscience Analyst.
License-Expression: MIT
License-File: LICENSE
License-File: docs/THIRD_PARTY_SOFTWARE.rst
Keywords: direct current resistivity,earth science,electromagnetics,geoh5,geophysics,geoscience,inverse problems,inversion,modeling,modelling,open science,simpeg
Author: Mira Geoscience
Author-email: support@mirageoscience.com
Maintainer: Benjamin Kary
Maintainer-email: benjamink@mirageoscience.com
Requires-Python: >=3.10,<4.0
Classifier: Development Status :: 4 - Beta
Classifier: Intended Audience :: Developers
Classifier: Intended Audience :: Science/Research
Classifier: Natural Language :: English
Classifier: Programming Language :: Python :: 3
Classifier: Programming Language :: Python :: 3.10
Classifier: Programming Language :: Python :: 3.11
Classifier: Programming Language :: Python :: 3.12
Classifier: Programming Language :: Python :: 3.13
Classifier: Programming Language :: Python :: 3.14
Classifier: Topic :: Scientific/Engineering
Classifier: Topic :: Scientific/Engineering :: Mathematics
Classifier: Topic :: Scientific/Engineering :: Physics
Classifier: Topic :: Software Development :: Libraries :: Python Modules
Requires-Dist: Rtree (>=1.2.0,<1.3.0)
Requires-Dist: dask (>=2025.3,<2025.4.dev)
Requires-Dist: discretize (==0.11.*)
Requires-Dist: distributed (>=2025.3,<2025.4.dev)
Requires-Dist: geoapps-utils (>=0.6.0rc1,<0.7.dev)
Requires-Dist: geoh5py (>=0.12.0rc2,<0.13.dev)
Requires-Dist: grid-apps (>=0.1.0rc1,<0.2.dev)
Requires-Dist: mira-simpeg[dask] (>=0.23.0.2rc1,<0.23.1.dev)
Requires-Dist: numpy (>=1.26.0,<1.27.0)
Requires-Dist: pydantic (>=2.11,<2.12)
Requires-Dist: pydiso (>=0.1.0,<0.2.dev)
Requires-Dist: python-mumps (>=0.0.3,<0.0.4.dev)
Requires-Dist: scikit-learn (>=1.6.0,<1.7.0)
Requires-Dist: scipy (>=1.14.0,<1.15.0)
Requires-Dist: tqdm (>=4.66.1,<5.0.0)
Requires-Dist: trimesh (>=4.1.3,<4.2.0)
Project-URL: Documentation, https://mirageoscience-simpeg-drivers.readthedocs-hosted.com/
Project-URL: Homepage, https://www.mirageoscience.com/mining-industry-software/python-integration/
Project-URL: Repository, https://github.com/MiraGeoscience/simpeg-drivers
